picterra/__init__.py
picterra/base_client.py
picterra/forge_client.py
picterra/nongeo.py
picterra/tracer_client.py
picterra-3.0.0.dist-info/licenses/LICENSE
picterra-3.0.0.dist-info/METADATA
picterra-3.0.0.dist-info/WHEEL
picterra-3.0.0.dist-info/top_level.txt
picterra-3.0.0.dist-info/RECORD
