Metadata-Version: 2.4
Name: picterra
Version: 3.0.0
Summary: Picterra API client
License-File: LICENSE
Requires-Dist: requests
Requires-Dist: urllib3>=1.26.0
Provides-Extra: test
Requires-Dist: pytest==7.1; extra == "test"
Requires-Dist: responses==0.22; extra == "test"
Requires-Dist: httpretty; extra == "test"
Provides-Extra: lint
Requires-Dist: flake8; extra == "lint"
Requires-Dist: mypy==1.8.0; extra == "lint"
Requires-Dist: types-requests; extra == "lint"
Dynamic: description
Dynamic: description-content-type
Dynamic: license-file
Dynamic: provides-extra
Dynamic: requires-dist
Dynamic: summary
